replay_identification/__init__.py
replay_identification/bins.py
replay_identification/core.py
replay_identification/decoders.py
replay_identification/detectors.py
replay_identification/discrete_state_transition.py
replay_identification/movement_state_transition.py
replay_identification/simulate.py
replay_identification/simulate_LFP.py
replay_identification/simulate_multiunit.py
replay_identification/simulate_speed.py
replay_identification/simulate_spiking.py
replay_identification/utilities.py
replay_identification/likelihoods/__init__.py
replay_identification/likelihoods/lfp_likelihood.py
replay_identification/likelihoods/multiunit_likelihood.py
replay_identification/likelihoods/multiunit_likelihood_integer.py
replay_identification/likelihoods/multiunit_likelihood_integer_gpu.py
replay_identification/likelihoods/multiunit_likelihood_track_graph.py
replay_identification/likelihoods/speed_likelihood.py
replay_identification/likelihoods/spiking_likelihood_glm.py
replay_identification/likelihoods/spiking_likelihood_kde.py
replay_identification/likelihoods/spiking_likelihood_kde_gpu.py
replay_identification-0.10.1.dev0.dist-info/LICENSE
replay_identification-0.10.1.dev0.dist-info/METADATA
replay_identification-0.10.1.dev0.dist-info/WHEEL
replay_identification-0.10.1.dev0.dist-info/top_level.txt
replay_identification-0.10.1.dev0.dist-info/RECORD
