Metadata-Version: 2.1
Name: replay-identification
Version: 0.10.1.dev0
Summary: Identify non-local events using multiple information sources
Home-page: https://github.com/Eden-Kramer-Lab/replay_identification
Author: Eric Denovellis
Author-email: edeno@bu.edu
License: MIT
License-File: LICENSE
Requires-Dist: numpy (>=1.11)
Requires-Dist: statsmodels
Requires-Dist: numba
Requires-Dist: matplotlib
Requires-Dist: xarray
Requires-Dist: scipy
Requires-Dist: scikit-learn
Requires-Dist: regularized-glm
Requires-Dist: seaborn
Requires-Dist: spectral-connectivity
Requires-Dist: tqdm
Requires-Dist: joblib
Requires-Dist: networkx
Requires-Dist: track-linearization
